setup.py
ezhil/EZTurtle.py
ezhil/EZWeb.py
ezhil/ExprsParser.py
ezhil/Interpreter.py
ezhil/__init__.py
ezhil/__main__.py
ezhil/ast.py
ezhil/errors.py
ezhil/exprs.py
ezhil/ezhil.py
ezhil/ezhil_library.py
ezhil/ezhil_messages.py
ezhil/ezhil_parser.py
ezhil/ezhil_program_utils.py
ezhil/ezhil_scanner.py
ezhil/ezhil_serializer.py
ezhil/ezhil_transforms.py
ezhil/ezhil_visualizer.py
ezhil/prettify.py
ezhil/profile.py
ezhil/runtime.py
ezhil/scanner.py
ezhil/theme.py
ezhil/transform.py
ezhil.egg-info/PKG-INFO
ezhil.egg-info/SOURCES.txt
ezhil.egg-info/dependency_links.txt
ezhil.egg-info/entry_points.txt
ezhil.egg-info/requires.txt
ezhil.egg-info/top_level.txt