Metadata-Version: 1.1
Name: ezhil
Version: 0.82
Summary: Ezhil - Tamil programming language implemented in Python
Home-page: https://github.com/arcturusannamalai/Ezhil-Lang
Author: Muthiah Annamalai
Author-email: ezhillang@gmail.com
License: GPLv3
Download-URL: https://github.com/arcturusannamalai/Ezhil-Lang/archive/latest.zip
Platform: PC
Platform: Linux
Platform: Mac
Classifier: N
Classifier: a
Classifier: t
Classifier: u
Classifier: r
Classifier: a
Classifier: l
Classifier:  
Classifier: L
Classifier: a
Classifier: n
Classifier: g
Classifier: u
Classifier: a
Classifier: g
Classifier: e
Classifier:  
Classifier: :
Classifier: :
Classifier:  
Classifier: T
Classifier: a
Classifier: m
Classifier: i
Classifier: l
